PyWiW/__init__.py
PyWiW/wiw.py
PyWiW-0.1.2.dist-info/LICENSE.txt
PyWiW-0.1.2.dist-info/METADATA
PyWiW-0.1.2.dist-info/WHEEL
PyWiW-0.1.2.dist-info/top_level.txt
PyWiW-0.1.2.dist-info/RECORD
