Metadata-Version: 2.1
Name: PyWiW
Version: 0.1.2
Summary: A When I Work API Python wrapper
Home-page: https://github.com/bannour-stuart/PyWiW
Author: Bakr Annour
Author-email: b.annour@stuart.com
License: MIT
Download-URL: https://github.com/bakr-a/PyWiW/archive/refs/tags/v0.1.1.tar.gz
Platform: UNKNOWN
Classifier: Development Status :: 5 - Production/Stable
Classifier: License :: OSI Approved :: MIT License
Classifier: Natural Language :: English
Classifier: Programming Language :: Python :: 3
Classifier: Topic :: Office/Business :: Scheduling
License-File: LICENSE.txt
Requires-Dist: requests (==2.23.0)
Requires-Dist: vcrpy (==4.0.2)
Requires-Dist: pytest (==5.4.2)
